{
    "의결서관리번호": "017057",
    "의결서제목": "(주)지에스리테일의 대규모소매업에 있어서의 특정불공정거래행위에 대한 건",
    "공개일자": "20220614",
    "의결서파일명": "e2838888-4eeb-4e73-81d3-32b1e14d04f5",
    "파일경로": "/2022/0614/",
    "피심인정보": [
        {
            "위반유형": "거래상지위남용",
            "세부위반유형": "대규모소매업에 있어서의 특정불공정거래행위",
            "조치유형": "과징금",
            "조치일자": "20120725",
            "피심인기업명": "(주)지에스리테일"
        },
        {
            "위반유형": "거래상지위남용",
            "세부위반유형": "대규모소매업에 있어서의 특정불공정거래행위",
            "조치유형": "시정명령",
            "조치일자": "20120725",
            "피심인기업명": "(주)지에스리테일"
        }
    ]
}