{
    "의결서관리번호": "017887",
    "의결서제목": "경상남도자동차매매사업조합의 사업자단체금지행위에 대한 건",
    "공개일자": "20220614",
    "의결서파일명": "e03e6a88-7d16-43dc-aa14-c42bf03ed181",
    "파일경로": "/2022/0614/",
    "피심인정보": [
        {
            "위반유형": "사업자단체금지행위",
            "세부위반유형": "단체-사업자수 제한",
            "조치유형": "과징금",
            "조치일자": "20131125",
            "피심인기업명": "경상남도자동차매매사업조합"
        },
        {
            "위반유형": "사업자단체금지행위",
            "세부위반유형": "단체-사업자수 제한",
            "조치유형": "시정명령",
            "조치일자": "20131125",
            "피심인기업명": "경상남도자동차매매사업조합"
        }
    ]
}