{
    "의결서관리번호": "016666",
    "의결서제목": "포천축산업협동조합의 거래상지위남용행위에 대한 건",
    "공개일자": "20220613",
    "의결서파일명": "87530d10-cfef-4b77-b23a-22a6ff22a7ed",
    "파일경로": "/2022/0613/",
    "피심인정보": [
        {
            "위반유형": "거래상지위남용",
            "세부위반유형": "불이익제공",
            "조치유형": "과징금",
            "조치일자": "20111205",
            "피심인기업명": "포천축산업협동조합"
        },
        {
            "위반유형": "거래상지위남용",
            "세부위반유형": "불이익제공",
            "조치유형": "시정명령",
            "조치일자": "20111205",
            "피심인기업명": "포천축산업협동조합"
        }
    ]
}