{
    "의결서관리번호": "017740",
    "의결서제목": "한국에스엠씨공압(주)의 불공정하도급거래행위에 대한 건",
    "공개일자": "20220706",
    "의결서파일명": "a3ba2505-ad28-405d-9bec-138c47b39fd3",
    "파일경로": "/2022/0706/",
    "피심인정보": [
        {
            "위반유형": "불공정하도급거래행위",
            "세부위반유형": "서면 미발급[구. 서면 미교부]",
            "조치유형": "시정명령",
            "조치일자": "20130912",
            "피심인기업명": "한국에스엠씨공압(주)"
        },
        {
            "위반유형": "불공정하도급거래행위",
            "세부위반유형": "부당한 하도급대금 결정",
            "조치유형": "과징금",
            "조치일자": "20130912",
            "피심인기업명": "한국에스엠씨공압(주)"
        },
        {
            "위반유형": "불공정하도급거래행위",
            "세부위반유형": "부당한 위탁취소(수령거부)[구. 발주취소(수령거부)]",
            "조치유형": "시정명령",
            "조치일자": "20130912",
            "피심인기업명": "한국에스엠씨공압(주)"
        }
    ]
}